pii_engine/__init__.py
pii_engine/app.py
pii_engine/cli.py
pii_engine/database.py
pii_engine/fabricator.py
pii_engine/config/__init__.py
pii_engine/config/pii_types.py
pii_engine/config/policies.yaml
pii_engine/core/__init__.py
pii_engine/core/encryptor.py
pii_engine/core/engine.py
pii_engine/core/hybrid_encryptor.py
pii_engine/core/masker.py
pii_engine/core/policy_engine.py
pii_engine/core/pseudo_storage_engine.py
pii_engine/core/pseudonymizer.py
pii_engine/core/tokenizer.py
pii_engine/middleware/__init__.py
pii_engine/middleware/api_gateway_middleware.py
pii_engine/middleware/fastapi_middleware.py
pii_engine/middleware/flask_middleware.py
pii_engine/middleware/hybrid_middleware.py
pii_engine/middleware/middleware.py
pii_engine/middleware/proxy_middleware.py
pii_engine/utils/__init__.py
pii_engine/utils/audit.py
pii_engine/utils/keygen.py
pii_engine-1.0.0.dist-info/licenses/LICENSE
pii_engine-1.0.0.dist-info/METADATA
pii_engine-1.0.0.dist-info/WHEEL
pii_engine-1.0.0.dist-info/entry_points.txt
pii_engine-1.0.0.dist-info/top_level.txt
pii_engine-1.0.0.dist-info/RECORD
