Metadata-Version: 2.4
Name: pii-engine
Version: 1.0.0
Summary: Enterprise PII Masking, Tokenization & Encryption Module
Author: PII Platform Team
Author-email: PII Platform Team <platform@company.com>
Maintainer-email: PII Platform Team <platform@company.com>
License: MIT
Project-URL: Homepage, https://github.com/company/pii-engine
Project-URL: Documentation, https://pii-engine.readthedocs.io/
Project-URL: Repository, https://github.com/company/pii-engine
Project-URL: Bug Tracker, https://github.com/company/pii-engine/issues
Keywords: pii,privacy,encryption,masking,tokenization,gdpr,compliance
Classifier: Development Status :: 5 - Production/Stable
Classifier: Intended Audience :: Developers
Classifier: License :: OSI Approved :: MIT License
Classifier: Programming Language :: Python :: 3
Classifier: Programming Language :: Python :: 3.8
Classifier: Programming Language :: Python :: 3.9
Classifier: Programming Language :: Python :: 3.10
Classifier: Programming Language :: Python :: 3.11
Classifier: Topic :: Security :: Cryptography
Classifier: Topic :: Software Development :: Libraries :: Python Modules
Requires-Python: >=3.8
License-File: LICENSE
Requires-Dist: cryptography>=3.4.8
Requires-Dist: faker>=18.0.0
Requires-Dist: python-dotenv>=0.19.0
Requires-Dist: pydantic>=1.8.0
Requires-Dist: asyncio-compat>=0.1.2
Provides-Extra: dev
Requires-Dist: pytest>=7.0.0; extra == "dev"
Requires-Dist: pytest-asyncio>=0.21.0; extra == "dev"
Requires-Dist: pytest-cov>=4.0.0; extra == "dev"
Requires-Dist: black>=22.0.0; extra == "dev"
Requires-Dist: isort>=5.10.0; extra == "dev"
Requires-Dist: flake8>=4.0.0; extra == "dev"
Requires-Dist: mypy>=0.950; extra == "dev"
Requires-Dist: bandit>=1.7.0; extra == "dev"
Requires-Dist: pre-commit>=2.17.0; extra == "dev"
Provides-Extra: fastapi
Requires-Dist: fastapi>=0.68.0; extra == "fastapi"
Requires-Dist: uvicorn>=0.15.0; extra == "fastapi"
Provides-Extra: flask
Requires-Dist: flask>=2.0.0; extra == "flask"
Provides-Extra: all
Requires-Dist: pii-engine[dev,fastapi,flask]; extra == "all"
Dynamic: author
Dynamic: license-file
Dynamic: requires-python
